syslog_rfc5424_formatter/__init__.py
syslog_rfc5424_formatter-1.2.3.dist-info/LICENSE.txt
syslog_rfc5424_formatter-1.2.3.dist-info/METADATA
syslog_rfc5424_formatter-1.2.3.dist-info/WHEEL
syslog_rfc5424_formatter-1.2.3.dist-info/top_level.txt
syslog_rfc5424_formatter-1.2.3.dist-info/RECORD
