Metadata-Version: 2.1
Name: syslog-rfc5424-formatter
Version: 1.2.3
Summary: Logging formatter which produces well-formatted RFC5424 Syslog Protocol messages
Home-page: https://github.com/easypost/syslog-rfc5424-formatter
Author: EasyPost
Author-email: oss@easypost.com
License: ISC
Project-URL: Issue Tracker, https://github.com/easypost/syslog-rfc5424-formatter/issues
Project-URL: Documentation, https://syslog-rfc5424-formatter.readthedocs.io/en/latest/
Keywords: logging
Platform: UNKNOWN
Classifier: Development Status :: 3 - Alpha
Classifier: Environment :: Console
Classifier: Programming Language :: Python
Classifier: Programming Language :: Python :: 2.7
Classifier: Programming Language :: Python :: 3.6
Classifier: Programming Language :: Python :: 3.7
Classifier: Programming Language :: Python :: 3.8
Classifier: Programming Language :: Python :: 3.9
Classifier: Operating System :: POSIX
Classifier: Intended Audience :: Developers
Classifier: License :: OSI Approved :: ISC License (ISCL)
Classifier: Topic :: System :: Logging
Requires-Python: >=2.7, !=3.0.*, !=3.1.*, !=3.2.*, !=3.3.*, !=3.4.*, !=3.5.*, <4
License-File: LICENSE.txt
